cb_exchange_lib/__init__.py
cb_exchange_lib/authentication.py
cb_exchange_lib/constants.py
cb_exchange_lib/endpoints.py
cb_exchange_lib/sessions.py
cb_exchange_lib/utils.py
cb_exchange_lib/websockets.py
cb_exchange_lib-3.0.3.dist-info/LICENSE
cb_exchange_lib-3.0.3.dist-info/METADATA
cb_exchange_lib-3.0.3.dist-info/WHEEL
cb_exchange_lib-3.0.3.dist-info/top_level.txt
cb_exchange_lib-3.0.3.dist-info/RECORD
