Metadata-Version: 2.1
Name: cb-exchange-lib
Version: 3.0.3
Summary: Coinbase Exchange API client library.
Home-page: https://github.com/ClaudiuDrug/cb-exchange-lib
Author: Claudiu DRUG
Author-email: claudiu.drug@outlook.com
License: MIT License
Project-URL: Bug Tracker, https://github.com/ClaudiuDrug/cb-exchange-lib/issues
Classifier: Programming Language :: Python :: 3.7
Classifier: License :: OSI Approved :: MIT License
Classifier: Operating System :: Microsoft :: Windows :: Windows 10
Classifier: Operating System :: POSIX :: Linux
Classifier: Intended Audience :: Developers
Classifier: Natural Language :: English
Classifier: Topic :: Software Development :: Libraries :: Python Modules
Classifier: Topic :: Utilities
Requires-Python: >=3.7
License-File: LICENSE
Requires-Dist: requests (>=2.30.0)
Requires-Dist: requests-cache (>=1.0.1)
Requires-Dist: requests-toolbelt (>=1.0.0)
Requires-Dist: urllib3 (>=2.0.2)
Requires-Dist: websocket-client (>=1.5.1)
